{
  "model": "EleutherAI/pythia-12b",
  "n_pred_tokens": 1233738,
  "overall_mean_loss": 1.9216803312301636,
  "by_position": {
    "word_initial": {
      "n": 580174,
      "mean_loss": 2.8110132217407227
    },
    "word_continuation": {
      "n": 273221,
      "mean_loss": 1.1991724967956543
    },
    "other": {
      "n": 380343,
      "mean_loss": 1.0841127634048462
    }
  },
  "by_depth": {
    "0_initial": {
      "n": 580174,
      "mean_loss": 2.8110132217407227
    },
    "1": {
      "n": 111688,
      "mean_loss": 1.6523529291152954
    },
    "2": {
      "n": 65341,
      "mean_loss": 1.1169512271881104
    },
    "3plus": {
      "n": 96192,
      "mean_loss": 0.728837251663208
    }
  },
  "by_seqband_position": {
    "early_lt128": {
      "word_initial": {
        "n": 72585,
        "mean_loss": 3.228126287460327
      },
      "word_continuation": {
        "n": 34258,
        "mean_loss": 1.6877989768981934
      }
    },
    "mid": {
      "word_initial": {
        "n": 362211,
        "mean_loss": 2.7601075172424316
      },
      "word_continuation": {
        "n": 171078,
        "mean_loss": 1.1348620653152466
      }
    },
    "late": {
      "word_initial": {
        "n": 145378,
        "mean_loss": 2.729583501815796
      },
      "word_continuation": {
        "n": 67885,
        "mean_loss": 1.1146568059921265
      }
    }
  },
  "by_freqdecile_position": {
    "0": {
      "freq_range": [
        1.0,
        14.0
      ],
      "word_initial": {
        "n": 55046,
        "mean_loss": 4.883960723876953
      },
      "word_continuation": {
        "n": 29401,
        "mean_loss": 2.582092761993408
      }
    },
    "1": {
      "freq_range": [
        14.0,
        35.0
      ],
      "word_initial": {
        "n": 55500,
        "mean_loss": 4.029918193817139
      },
      "word_continuation": {
        "n": 29716,
        "mean_loss": 1.7176874876022339
      }
    },
    "2": {
      "freq_range": [
        35.0,
        69.0
      ],
      "word_initial": {
        "n": 55345,
        "mean_loss": 3.7350637912750244
      },
      "word_continuation": {
        "n": 28638,
        "mean_loss": 1.35489821434021
      }
    },
    "3": {
      "freq_range": [
        69.0,
        129.0
      ],
      "word_initial": {
        "n": 55452,
        "mean_loss": 3.3879282474517822
      },
      "word_continuation": {
        "n": 32230,
        "mean_loss": 1.0750685930252075
      }
    },
    "4": {
      "freq_range": [
        129.0,
        235.0
      ],
      "word_initial": {
        "n": 50479,
        "mean_loss": 3.211611270904541
      },
      "word_continuation": {
        "n": 34160,
        "mean_loss": 0.9030819535255432
      }
    },
    "5": {
      "freq_range": [
        235.0,
        465.0
      ],
      "word_initial": {
        "n": 56546,
        "mean_loss": 2.8149969577789307
      },
      "word_continuation": {
        "n": 29155,
        "mean_loss": 0.7680383920669556
      }
    },
    "6": {
      "freq_range": [
        465.0,
        982.0
      ],
      "word_initial": {
        "n": 52215,
        "mean_loss": 2.4488041400909424
      },
      "word_continuation": {
        "n": 32724,
        "mean_loss": 1.0562498569488525
      }
    },
    "7": {
      "freq_range": [
        982.0,
        2871.0
      ],
      "word_initial": {
        "n": 51711,
        "mean_loss": 2.087108612060547
      },
      "word_continuation": {
        "n": 33872,
        "mean_loss": 0.9443358182907104
      }
    },
    "8": {
      "freq_range": [
        2871.0,
        12358.0
      ],
      "word_initial": {
        "n": 53459,
        "mean_loss": 1.4800429344177246
      },
      "word_continuation": {
        "n": 23325,
        "mean_loss": 0.3188164532184601
      }
    },
    "9": {
      "freq_range": [
        12358.0,
        32401.0
      ],
      "word_initial": {
        "n": 94421,
        "mean_loss": 1.1393717527389526
      },
      "word_continuation": {
        "n": 0,
        "mean_loss": null
      }
    }
  },
  "by_wordfreqdecile_position": {
    "0": {
      "wordfreq_range": [
        1.0,
        1.0
      ],
      "word_initial": {
        "n": 0,
        "mean_loss": null
      },
      "word_continuation": {
        "n": 0,
        "mean_loss": null
      }
    },
    "1": {
      "wordfreq_range": [
        1.0,
        2.0
      ],
      "word_initial": {
        "n": 44485,
        "mean_loss": 4.198589324951172
      },
      "word_continuation": {
        "n": 116216,
        "mean_loss": 1.512601375579834
      }
    },
    "2": {
      "wordfreq_range": [
        2.0,
        5.0
      ],
      "word_initial": {
        "n": 44810,
        "mean_loss": 4.076181888580322
      },
      "word_continuation": {
        "n": 50251,
        "mean_loss": 1.1293584108352661
      }
    },
    "3": {
      "wordfreq_range": [
        5.0,
        12.0
      ],
      "word_initial": {
        "n": 48494,
        "mean_loss": 3.8539681434631348
      },
      "word_continuation": {
        "n": 30269,
        "mean_loss": 0.848659336566925
      }
    },
    "4": {
      "wordfreq_range": [
        12.0,
        32.0
      ],
      "word_initial": {
        "n": 64423,
        "mean_loss": 3.538079261779785
      },
      "word_continuation": {
        "n": 26797,
        "mean_loss": 0.8417258858680725
      }
    },
    "5": {
      "wordfreq_range": [
        32.0,
        86.0
      ],
      "word_initial": {
        "n": 66555,
        "mean_loss": 3.2829620838165283
      },
      "word_continuation": {
        "n": 19470,
        "mean_loss": 0.8491493463516235
      }
    },
    "6": {
      "wordfreq_range": [
        86.0,
        270.0
      ],
      "word_initial": {
        "n": 72729,
        "mean_loss": 2.998215675354004
      },
      "word_continuation": {
        "n": 12697,
        "mean_loss": 1.1322886943817139
      }
    },
    "7": {
      "wordfreq_range": [
        270.0,
        1543.0
      ],
      "word_initial": {
        "n": 74750,
        "mean_loss": 2.3768861293792725
      },
      "word_continuation": {
        "n": 9698,
        "mean_loss": 0.9752986431121826
      }
    },
    "8": {
      "wordfreq_range": [
        1543.0,
        12226.0
      ],
      "word_initial": {
        "n": 69897,
        "mean_loss": 1.7992351055145264
      },
      "word_continuation": {
        "n": 7724,
        "mean_loss": 0.8075776100158691
      }
    },
    "9": {
      "wordfreq_range": [
        12226.0,
        32419.0
      ],
      "word_initial": {
        "n": 94031,
        "mean_loss": 1.1340093612670898
      },
      "word_continuation": {
        "n": 99,
        "mean_loss": 2.5211880207061768
      }
    }
  },
  "by_position_multitokenonly": {
    "word_initial": {
      "n": 159601,
      "mean_loss": 3.241570472717285
    },
    "word_continuation": {
      "n": 273221,
      "mean_loss": 1.1991724967956543
    }
  },
  "by_wordlen_position": {
    "len2_init": {
      "n": 96521,
      "mean_loss": 3.106853723526001
    },
    "len2_cont": {
      "n": 53079,
      "mean_loss": 1.4859949350357056
    },
    "len3_init": {
      "n": 33069,
      "mean_loss": 3.8429646492004395
    },
    "len3_cont": {
      "n": 61634,
      "mean_loss": 1.2570316791534424
    },
    "len4plus_init": {
      "n": 30011,
      "mean_loss": 3.012171506881714
    },
    "len4plus_cont": {
      "n": 158508,
      "mean_loss": 1.0806269645690918
    }
  },
  "by_wordfreqdecile_position_multitokenonly": {
    "0": {
      "wordfreq_range": [
        1.0,
        1.0
      ],
      "word_initial": {
        "n": 0,
        "mean_loss": null
      },
      "word_continuation": {
        "n": 0,
        "mean_loss": null
      }
    },
    "1": {
      "wordfreq_range": [
        1.0,
        1.0
      ],
      "word_initial": {
        "n": 0,
        "mean_loss": null
      },
      "word_continuation": {
        "n": 0,
        "mean_loss": null
      }
    },
    "2": {
      "wordfreq_range": [
        1.0,
        1.0
      ],
      "word_initial": {
        "n": 0,
        "mean_loss": null
      },
      "word_continuation": {
        "n": 0,
        "mean_loss": null
      }
    },
    "3": {
      "wordfreq_range": [
        1.0,
        2.0
      ],
      "word_initial": {
        "n": 41299,
        "mean_loss": 4.097557067871094
      },
      "word_continuation": {
        "n": 116216,
        "mean_loss": 1.512601375579834
      }
    },
    "4": {
      "wordfreq_range": [
        2.0,
        3.0
      ],
      "word_initial": {
        "n": 16082,
        "mean_loss": 3.8899762630462646
      },
      "word_continuation": {
        "n": 25969,
        "mean_loss": 1.2391043901443481
      }
    },
    "5": {
      "wordfreq_range": [
        3.0,
        6.0
      ],
      "word_initial": {
        "n": 23351,
        "mean_loss": 3.6656603813171387
      },
      "word_continuation": {
        "n": 30994,
        "mean_loss": 0.9917290806770325
      }
    },
    "6": {
      "wordfreq_range": [
        6.0,
        12.0
      ],
      "word_initial": {
        "n": 21226,
        "mean_loss": 3.2882044315338135
      },
      "word_continuation": {
        "n": 23557,
        "mean_loss": 0.828777015209198
      }
    },
    "7": {
      "wordfreq_range": [
        12.0,
        28.0
      ],
      "word_initial": {
        "n": 22671,
        "mean_loss": 2.9340338706970215
      },
      "word_continuation": {
        "n": 24064,
        "mean_loss": 0.8384657502174377
      }
    },
    "8": {
      "wordfreq_range": [
        28.0,
        103.0
      ],
      "word_initial": {
        "n": 19605,
        "mean_loss": 2.2097904682159424
      },
      "word_continuation": {
        "n": 24327,
        "mean_loss": 0.882951557636261
      }
    },
    "9": {
      "wordfreq_range": [
        103.0,
        32419.0
      ],
      "word_initial": {
        "n": 15367,
        "mean_loss": 1.3237226009368896
      },
      "word_continuation": {
        "n": 28094,
        "mean_loss": 0.9879229664802551
      }
    }
  },
  "by_wordfreqdecile_position_per_word": {
    "0": {
      "wordfreq_range": [
        1.0,
        1.0
      ],
      "n_words": 0,
      "word_initial": {
        "n_words": 0,
        "mean_loss": null
      },
      "word_continuation": {
        "n_words": 0,
        "mean_loss": null
      }
    },
    "1": {
      "wordfreq_range": [
        1.0,
        1.0
      ],
      "n_words": 0,
      "word_initial": {
        "n_words": 0,
        "mean_loss": null
      },
      "word_continuation": {
        "n_words": 0,
        "mean_loss": null
      }
    },
    "2": {
      "wordfreq_range": [
        1.0,
        2.0
      ],
      "n_words": 56162,
      "word_initial": {
        "n_words": 41299,
        "mean_loss": 4.097556611963908
      },
      "word_continuation": {
        "n_words": 46702,
        "mean_loss": 1.648219376935379
      }
    },
    "3": {
      "wordfreq_range": [
        2.0,
        3.0
      ],
      "n_words": 19515,
      "word_initial": {
        "n_words": 16082,
        "mean_loss": 3.889976360735437
      },
      "word_continuation": {
        "n_words": 14439,
        "mean_loss": 1.2107424876515331
      }
    },
    "4": {
      "wordfreq_range": [
        3.0,
        6.0
      ],
      "n_words": 27672,
      "word_initial": {
        "n_words": 23351,
        "mean_loss": 3.6656604759190983
      },
      "word_continuation": {
        "n_words": 19174,
        "mean_loss": 0.9953320255572474
      }
    },
    "5": {
      "wordfreq_range": [
        6.0,
        11.0
      ],
      "n_words": 21402,
      "word_initial": {
        "n_words": 18532,
        "mean_loss": 3.3002461514213137
      },
      "word_continuation": {
        "n_words": 13679,
        "mean_loss": 0.8782261074867435
      }
    },
    "6": {
      "wordfreq_range": [
        11.0,
        21.0
      ],
      "n_words": 21437,
      "word_initial": {
        "n_words": 18159,
        "mean_loss": 3.0281436217196
      },
      "word_continuation": {
        "n_words": 13417,
        "mean_loss": 0.9103588582755717
      }
    },
    "7": {
      "wordfreq_range": [
        21.0,
        48.0
      ],
      "n_words": 20871,
      "word_initial": {
        "n_words": 16960,
        "mean_loss": 2.6173733991345363
      },
      "word_continuation": {
        "n_words": 12633,
        "mean_loss": 0.9293932526815867
      }
    },
    "8": {
      "wordfreq_range": [
        48.0,
        175.0
      ],
      "n_words": 21302,
      "word_initial": {
        "n_words": 15535,
        "mean_loss": 1.8025341013235685
      },
      "word_continuation": {
        "n_words": 13737,
        "mean_loss": 1.1368678731012
      }
    },
    "9": {
      "wordfreq_range": [
        175.0,
        32419.0
      ],
      "n_words": 21046,
      "word_initial": {
        "n_words": 9683,
        "mean_loss": 1.1810644060096216
      },
      "word_continuation": {
        "n_words": 14757,
        "mean_loss": 1.3372012391820827
      }
    }
  },
  "per_word_summary": {
    "n_multitoken_words": 209407,
    "init_loss_mean": 3.241570472717285,
    "cont_loss_mean": 1.2445323467254639,
    "init_loss_std": 3.1063592433929443,
    "cont_loss_std": 1.987656593322754,
    "diff_mean": 3.2252085208892822,
    "diff_std": 3.3893215656280518
  }
}