{
  "model": "EleutherAI/pythia-1b-deduped",
  "n_pred_tokens": 1233738,
  "overall_mean_loss": 2.0719974040985107,
  "by_position": {
    "word_initial": {
      "n": 580174,
      "mean_loss": 3.032501697540283
    },
    "word_continuation": {
      "n": 273221,
      "mean_loss": 1.334798812866211
    },
    "other": {
      "n": 380343,
      "mean_loss": 1.1364171504974365
    }
  },
  "by_depth": {
    "0_initial": {
      "n": 580174,
      "mean_loss": 3.032501697540283
    },
    "1": {
      "n": 111688,
      "mean_loss": 1.8055965900421143
    },
    "2": {
      "n": 65341,
      "mean_loss": 1.2569169998168945
    },
    "3plus": {
      "n": 96192,
      "mean_loss": 0.841061532497406
    }
  },
  "by_seqband_position": {
    "early_lt128": {
      "word_initial": {
        "n": 72585,
        "mean_loss": 3.442213773727417
      },
      "word_continuation": {
        "n": 34258,
        "mean_loss": 1.837531566619873
      }
    },
    "mid": {
      "word_initial": {
        "n": 362211,
        "mean_loss": 2.9831814765930176
      },
      "word_continuation": {
        "n": 171078,
        "mean_loss": 1.2691850662231445
      }
    },
    "late": {
      "word_initial": {
        "n": 145378,
        "mean_loss": 2.9508204460144043
      },
      "word_continuation": {
        "n": 67885,
        "mean_loss": 1.2464500665664673
      }
    }
  },
  "by_freqdecile_position": {
    "0": {
      "freq_range": [
        1.0,
        14.0
      ],
      "word_initial": {
        "n": 55046,
        "mean_loss": 5.2837443351745605
      },
      "word_continuation": {
        "n": 29401,
        "mean_loss": 2.8171448707580566
      }
    },
    "1": {
      "freq_range": [
        14.0,
        35.0
      ],
      "word_initial": {
        "n": 55500,
        "mean_loss": 4.40610933303833
      },
      "word_continuation": {
        "n": 29716,
        "mean_loss": 1.9264917373657227
      }
    },
    "2": {
      "freq_range": [
        35.0,
        69.0
      ],
      "word_initial": {
        "n": 55345,
        "mean_loss": 4.076391696929932
      },
      "word_continuation": {
        "n": 28638,
        "mean_loss": 1.5533493757247925
      }
    },
    "3": {
      "freq_range": [
        69.0,
        129.0
      ],
      "word_initial": {
        "n": 55452,
        "mean_loss": 3.6839704513549805
      },
      "word_continuation": {
        "n": 32230,
        "mean_loss": 1.2280367612838745
      }
    },
    "4": {
      "freq_range": [
        129.0,
        235.0
      ],
      "word_initial": {
        "n": 50479,
        "mean_loss": 3.46927547454834
      },
      "word_continuation": {
        "n": 34160,
        "mean_loss": 1.015225887298584
      }
    },
    "5": {
      "freq_range": [
        235.0,
        465.0
      ],
      "word_initial": {
        "n": 56546,
        "mean_loss": 3.027026414871216
      },
      "word_continuation": {
        "n": 29155,
        "mean_loss": 0.8577374815940857
      }
    },
    "6": {
      "freq_range": [
        465.0,
        982.0
      ],
      "word_initial": {
        "n": 52215,
        "mean_loss": 2.628427028656006
      },
      "word_continuation": {
        "n": 32724,
        "mean_loss": 1.1786236763000488
      }
    },
    "7": {
      "freq_range": [
        982.0,
        2871.0
      ],
      "word_initial": {
        "n": 51711,
        "mean_loss": 2.207871198654175
      },
      "word_continuation": {
        "n": 33872,
        "mean_loss": 1.0469472408294678
      }
    },
    "8": {
      "freq_range": [
        2871.0,
        12358.0
      ],
      "word_initial": {
        "n": 53459,
        "mean_loss": 1.570723295211792
      },
      "word_continuation": {
        "n": 23325,
        "mean_loss": 0.2931268513202667
      }
    },
    "9": {
      "freq_range": [
        12358.0,
        32401.0
      ],
      "word_initial": {
        "n": 94421,
        "mean_loss": 1.1906615495681763
      },
      "word_continuation": {
        "n": 0,
        "mean_loss": null
      }
    }
  },
  "by_wordfreqdecile_position": {
    "0": {
      "wordfreq_range": [
        1.0,
        1.0
      ],
      "word_initial": {
        "n": 0,
        "mean_loss": null
      },
      "word_continuation": {
        "n": 0,
        "mean_loss": null
      }
    },
    "1": {
      "wordfreq_range": [
        1.0,
        2.0
      ],
      "word_initial": {
        "n": 44485,
        "mean_loss": 4.6126627922058105
      },
      "word_continuation": {
        "n": 116216,
        "mean_loss": 1.7069199085235596
      }
    },
    "2": {
      "wordfreq_range": [
        2.0,
        5.0
      ],
      "word_initial": {
        "n": 44810,
        "mean_loss": 4.4705424308776855
      },
      "word_continuation": {
        "n": 50251,
        "mean_loss": 1.2957156896591187
      }
    },
    "3": {
      "wordfreq_range": [
        5.0,
        12.0
      ],
      "word_initial": {
        "n": 48494,
        "mean_loss": 4.217389106750488
      },
      "word_continuation": {
        "n": 30269,
        "mean_loss": 0.9387050271034241
      }
    },
    "4": {
      "wordfreq_range": [
        12.0,
        32.0
      ],
      "word_initial": {
        "n": 64423,
        "mean_loss": 3.863940715789795
      },
      "word_continuation": {
        "n": 26797,
        "mean_loss": 0.9022713303565979
      }
    },
    "5": {
      "wordfreq_range": [
        32.0,
        86.0
      ],
      "word_initial": {
        "n": 66555,
        "mean_loss": 3.5488200187683105
      },
      "word_continuation": {
        "n": 19470,
        "mean_loss": 0.9029586911201477
      }
    },
    "6": {
      "wordfreq_range": [
        86.0,
        270.0
      ],
      "word_initial": {
        "n": 72729,
        "mean_loss": 3.198413372039795
      },
      "word_continuation": {
        "n": 12697,
        "mean_loss": 1.1801081895828247
      }
    },
    "7": {
      "wordfreq_range": [
        270.0,
        1543.0
      ],
      "word_initial": {
        "n": 74750,
        "mean_loss": 2.518261194229126
      },
      "word_continuation": {
        "n": 9698,
        "mean_loss": 0.9605106711387634
      }
    },
    "8": {
      "wordfreq_range": [
        1543.0,
        12226.0
      ],
      "word_initial": {
        "n": 69897,
        "mean_loss": 1.8879597187042236
      },
      "word_continuation": {
        "n": 7724,
        "mean_loss": 0.8418609499931335
      }
    },
    "9": {
      "wordfreq_range": [
        12226.0,
        32419.0
      ],
      "word_initial": {
        "n": 94031,
        "mean_loss": 1.1847437620162964
      },
      "word_continuation": {
        "n": 99,
        "mean_loss": 2.4123690128326416
      }
    }
  },
  "by_position_multitokenonly": {
    "word_initial": {
      "n": 159601,
      "mean_loss": 3.5892930030822754
    },
    "word_continuation": {
      "n": 273221,
      "mean_loss": 1.334798812866211
    }
  },
  "by_wordlen_position": {
    "len2_init": {
      "n": 96521,
      "mean_loss": 3.429844856262207
    },
    "len2_cont": {
      "n": 53079,
      "mean_loss": 1.5911904573440552
    },
    "len3_init": {
      "n": 33069,
      "mean_loss": 4.279534816741943
    },
    "len3_cont": {
      "n": 61634,
      "mean_loss": 1.3908392190933228
    },
    "len4plus_init": {
      "n": 30011,
      "mean_loss": 3.3415346145629883
    },
    "len4plus_cont": {
      "n": 158508,
      "mean_loss": 1.2271511554718018
    }
  },
  "by_wordfreqdecile_position_multitokenonly": {
    "0": {
      "wordfreq_range": [
        1.0,
        1.0
      ],
      "word_initial": {
        "n": 0,
        "mean_loss": null
      },
      "word_continuation": {
        "n": 0,
        "mean_loss": null
      }
    },
    "1": {
      "wordfreq_range": [
        1.0,
        1.0
      ],
      "word_initial": {
        "n": 0,
        "mean_loss": null
      },
      "word_continuation": {
        "n": 0,
        "mean_loss": null
      }
    },
    "2": {
      "wordfreq_range": [
        1.0,
        1.0
      ],
      "word_initial": {
        "n": 0,
        "mean_loss": null
      },
      "word_continuation": {
        "n": 0,
        "mean_loss": null
      }
    },
    "3": {
      "wordfreq_range": [
        1.0,
        2.0
      ],
      "word_initial": {
        "n": 41299,
        "mean_loss": 4.514232158660889
      },
      "word_continuation": {
        "n": 116216,
        "mean_loss": 1.7069199085235596
      }
    },
    "4": {
      "wordfreq_range": [
        2.0,
        3.0
      ],
      "word_initial": {
        "n": 16082,
        "mean_loss": 4.293540000915527
      },
      "word_continuation": {
        "n": 25969,
        "mean_loss": 1.4101293087005615
      }
    },
    "5": {
      "wordfreq_range": [
        3.0,
        6.0
      ],
      "word_initial": {
        "n": 23351,
        "mean_loss": 4.067740440368652
      },
      "word_continuation": {
        "n": 30994,
        "mean_loss": 1.144913673400879
      }
    },
    "6": {
      "wordfreq_range": [
        6.0,
        12.0
      ],
      "word_initial": {
        "n": 21226,
        "mean_loss": 3.660806894302368
      },
      "word_continuation": {
        "n": 23557,
        "mean_loss": 0.9092654585838318
      }
    },
    "7": {
      "wordfreq_range": [
        12.0,
        28.0
      ],
      "word_initial": {
        "n": 22671,
        "mean_loss": 3.285159111022949
      },
      "word_continuation": {
        "n": 24064,
        "mean_loss": 0.901627779006958
      }
    },
    "8": {
      "wordfreq_range": [
        28.0,
        103.0
      ],
      "word_initial": {
        "n": 19605,
        "mean_loss": 2.4308040142059326
      },
      "word_continuation": {
        "n": 24327,
        "mean_loss": 0.9336646199226379
      }
    },
    "9": {
      "wordfreq_range": [
        103.0,
        32419.0
      ],
      "word_initial": {
        "n": 15367,
        "mean_loss": 1.4673606157302856
      },
      "word_continuation": {
        "n": 28094,
        "mean_loss": 1.0104992389678955
      }
    }
  },
  "by_wordfreqdecile_position_per_word": {
    "0": {
      "wordfreq_range": [
        1.0,
        1.0
      ],
      "n_words": 0,
      "word_initial": {
        "n_words": 0,
        "mean_loss": null
      },
      "word_continuation": {
        "n_words": 0,
        "mean_loss": null
      }
    },
    "1": {
      "wordfreq_range": [
        1.0,
        1.0
      ],
      "n_words": 0,
      "word_initial": {
        "n_words": 0,
        "mean_loss": null
      },
      "word_continuation": {
        "n_words": 0,
        "mean_loss": null
      }
    },
    "2": {
      "wordfreq_range": [
        1.0,
        2.0
      ],
      "n_words": 56162,
      "word_initial": {
        "n_words": 41299,
        "mean_loss": 4.5142319970756155
      },
      "word_continuation": {
        "n_words": 46702,
        "mean_loss": 1.8444307894505647
      }
    },
    "3": {
      "wordfreq_range": [
        2.0,
        3.0
      ],
      "n_words": 19515,
      "word_initial": {
        "n_words": 16082,
        "mean_loss": 4.29354003155704
      },
      "word_continuation": {
        "n_words": 14439,
        "mean_loss": 1.3823297444385796
      }
    },
    "4": {
      "wordfreq_range": [
        3.0,
        6.0
      ],
      "n_words": 27672,
      "word_initial": {
        "n_words": 23351,
        "mean_loss": 4.067740311072073
      },
      "word_continuation": {
        "n_words": 19174,
        "mean_loss": 1.1365180218035806
      }
    },
    "5": {
      "wordfreq_range": [
        6.0,
        11.0
      ],
      "n_words": 21402,
      "word_initial": {
        "n_words": 18532,
        "mean_loss": 3.6656896779099513
      },
      "word_continuation": {
        "n_words": 13679,
        "mean_loss": 0.9506464008201946
      }
    },
    "6": {
      "wordfreq_range": [
        11.0,
        21.0
      ],
      "n_words": 21437,
      "word_initial": {
        "n_words": 18159,
        "mean_loss": 3.3974589245881157
      },
      "word_continuation": {
        "n_words": 13417,
        "mean_loss": 0.9773192260439229
      }
    },
    "7": {
      "wordfreq_range": [
        21.0,
        48.0
      ],
      "n_words": 20871,
      "word_initial": {
        "n_words": 16960,
        "mean_loss": 2.907887164804492
      },
      "word_continuation": {
        "n_words": 12633,
        "mean_loss": 0.9635103610840301
      }
    },
    "8": {
      "wordfreq_range": [
        48.0,
        175.0
      ],
      "n_words": 21302,
      "word_initial": {
        "n_words": 15535,
        "mean_loss": 1.9797320242219143
      },
      "word_continuation": {
        "n_words": 13737,
        "mean_loss": 1.1981141658034875
      }
    },
    "9": {
      "wordfreq_range": [
        175.0,
        32419.0
      ],
      "n_words": 21046,
      "word_initial": {
        "n_words": 9683,
        "mean_loss": 1.3102408530902556
      },
      "word_continuation": {
        "n_words": 14757,
        "mean_loss": 1.3497274563323207
      }
    }
  },
  "per_word_summary": {
    "n_multitoken_words": 209407,
    "init_loss_mean": 3.5892930030822754,
    "cont_loss_mean": 1.363655686378479,
    "init_loss_std": 3.235464096069336,
    "cont_loss_std": 2.0241634845733643,
    "diff_mean": 3.519883394241333,
    "diff_std": 3.473341464996338
  }
}